Workbook

Sheet Assumptions
A1: MODEL ASSUMPTIONS
A2: REVENUE ASSUMPTIONS | B2: Values
A3: Starting MRR | B3: =SUM([1]Q1_ARR_by_contract!$D$2:$D$4) -> 456116.6
A4: Monthly Growth rate | B4: 0.03
A5: Annual Churn Rate | B5: 0.26536987
A6: Average Revenue Per User (ARPU) | B6: =SUM([1]Q1_ARR_by_contract!$D$2:$D$4)/SUM([1]Q1_ARR_by_contract!$B$2:$B$4) -> 64.761692
A9: COST ASSUMPTIONS
A10: Gross Margin % | B10: 0.72
A11: Sales & Marketing % | B11: 0.25
A12: R&D % | B12: 0.15
A13: G&A % | B13: 0.1
A15: MODEL SETTING
A16: Start Date | B16: 45292
A17: Forecast Period (months) | B17: 24
A18: Discount Rate (WACC) | B18: 0.1

Sheet Revenue Model
A1: REVENUE MODEL | B1: Month 1 | C1: Month 2 | D1: Month 3 | E1: Month 4 | F1: Month 5 | G1: Month 6 | H1: Month 7 | I1: Month 8 | J1: Month 9 | K1: Month 10 | L1: Month 11 | M1: Month 12 | N1: Month 13 | O1: Month 14 | P1: Month 15 | Q1: Month 16 | R1: Month 17 | S1: Month 18 | T1: Month 19 | U1: Month 20 | V1: Month 21 | W1: Month 22 | X1: Month 23 | Y1: Month 24
A5: Month | B5: 1 | C5: 2 | D5: 3 | E5: 4 | F5: 5 | G5: 6 | H5: 7 | I5: 8 | J5: 9 | K5: 10 | L5: 11 | M5: 12 | N5: 13 | O5: 14 | P5: 15 | Q5: 16 | R5: 17 | S5: 18 | T5: 19 | U5: 20 | V5: 21 | W5: 22 | X5: 23 | Y5: 24
A6: Date | B6: 45292 | C6: 45323 | D6: 45352 | E6: 45383 | F6: 45413 | G6: 45444 | H6: 45474 | I6: 45505 | J6: 45536 | K6: 45566 | L6: 45597 | M6: 45627 | N6: 45658 | O6: 45689 | P6: 45717 | Q6: 45748 | R6: 45778 | S6: 45809 | T6: 45839 | U6: 45870 | V6: 45901 | W6: 45931 | X6: 45962 | Y6: 45992
A7: Beginning Customers | B7: =Assumptions!$B$3/Assumptions!$B$6 -> 7043 | C7: =B10 -> 7098 | D7: =C10 -> 7154 | E7: =D10 -> 7211 | F7: =E10 -> 7268 | G7: =F10 -> 7325 | H7: =G10 -> 7383 | I7: =H10 -> 7441 | J7: =I10 -> 7499 | ... Y7: =X10 -> 8438
A8: New Customers Added | B8: =ROUND(B7*Assumptions!$B$4, 0) -> 211 | C8: =ROUND(C7*Assumptions!$B$4, 0) -> 213 | D8: =ROUND(D7*Assumptions!$B$4, 0) -> 215 | E8: =ROUND(E7*Assumptions!$B$4, 0) -> 216 | F8: =ROUND(F7*Assumptions!$B$4, 0) -> 218 | G8: =ROUND(G7*Assumptions!$B$4, 0) -> 220 | H8: =ROUND(H7*Assumptions!$B$4, 0) -> 221 | I8: =ROUND(I7*Assumptions!$B$4, 0) -> 223 | ... Y8: =ROUND(Y7*Assumptions!$B$4, 0) -> 253
A9: Churned Customers | B9: =ROUND(B7*(Assumptions!$B$5/12),0) -> 156 | C9: =ROUND(C7*(Assumptions!$B$5/12),0) -> 157 | D9: =ROUND(D7*(Assumptions!$B$5/12),0) -> 158 | E9: =ROUND(E7*(Assumptions!$B$5/12),0) -> 159 | F9: =ROUND(F7*(Assumptions!$B$5/12),0) -> 161 | G9: =ROUND(G7*(Assumptions!$B$5/12),0) -> 162 | H9: =ROUND(H7*(Assumptions!$B$5/12),0) -> 163 | I9: =ROUND(I7*(Assumptions!$B$5/12),0) -> 165 | ... Y9: =ROUND(Y7*(Assumptions!$B$5/12),0) -> 187
A10: Ending Customers | B10: =B7+B8-B9 -> 7098 | C10: =C7+C8-C9 -> 7154 | D10: =D7+D8-D9 -> 7211 | E10: =E7+E8-E9 -> 7268 | F10: =F7+F8-F9 -> 7325 | G10: =G7+G8-G9 -> 7383 | H10: =H7+H8-H9 -> 7441 | I10: =I7+I8-I9 -> 7499 | ... Y10: =Y7+Y8-Y9 -> 8504
A12: ARPU | B12: =Assumptions!$B$6 -> 64.761692 | C12: =Assumptions!$B$6 -> 64.761692 | D12: =Assumptions!$B$6 -> 64.761692 | E12: =Assumptions!$B$6 -> 64.761692 | F12: =Assumptions!$B$6 -> 64.761692 | G12: =Assumptions!$B$6 -> 64.761692 | H12: =Assumptions!$B$6 -> 64.761692 | I12: =Assumptions!$B$6 -> 64.761692 | ... Y12: =Assumptions!$B$6 -> 64.761692
A13: MRR | B13: =Assumptions!$B$3 -> 456116.6 | C13: =C12*C10 -> 463305.15 | D13: =D12*D10 -> 466996.56 | E13: =E12*E10 -> 470687.98 | F13: =F12*F10 -> 474379.4 | G13: =G12*G10 -> 478135.58 | H13: =H12*H10 -> 481891.75 | I13: =I12*I10 -> 485647.93 | J13: =J12*J10 -> 489468.87 | ... Y13: =Y12*Y10 -> 550733.43
A14: ARR | B14: =Assumptions!$B$3*12 -> 5473399.2 | C14: =C13*12 -> 5559661.8 | D14: =D13*12 -> 5603958.8 | E14: =E13*12 -> 5648255.8 | F14: =F13*12 -> 5692552.8 | G14: =G13*12 -> 5737626.9 | H14: =H13*12 -> 5782701 | I14: =I13*12 -> 5827775.2 | J14: =J13*12 -> 5873626.5 | ... Y14: =Y13*12 -> 6608801.2
A16: MRR Growth % | B16: =(C14-B14)/B14 -> 0.015760329 | C16: =(D14-C14)/C14 -> 0.0079675706 | D16: =(E14-D14)/D14 -> 0.0079045902 | E16: =(F14-E14)/E14 -> 0.0078425977 | F16: =(G14-F14)/F14 -> 0.0079180887 | G16: =(H14-G14)/G14 -> 0.0078558851 | H16: =(I14-H14)/H14 -> 0.0077946513 | I16: =(J14-I14)/I14 -> 0.0078677157 | ... X16: =(Y14-X14)/X14 -> 0.0078217587 | Y16: -
A17: Churn Rate (monthly) | B17: =Assumptions!$B$5/12 -> 0.022114156 | C17: =Assumptions!$B$5/12 -> 0.022114156 | D17: =Assumptions!$B$5/12 -> 0.022114156 | E17: =Assumptions!$B$5/12 -> 0.022114156 | F17: =Assumptions!$B$5/12 -> 0.022114156 | G17: =Assumptions!$B$5/12 -> 0.022114156 | H17: =Assumptions!$B$5/12 -> 0.022114156 | I17: =Assumptions!$B$5/12 -> 0.022114156 | ... X17: =Assumptions!$B$5/12 -> 0.022114156 | Y17: -

Sheet P&L
A1: PROFIT AND LOSS STATEMENT - INCOME STATEMENT | B1: Month 1 | C1: Month 2 | D1: Month 3 | E1: Month 4 | F1: Month 5 | G1: Month 6 | H1: Month 7 | I1: Month 8 | J1: Month 9 | K1: Month 10 | L1: Month 11 | M1: Month 12 | N1: Month 13 | O1: Month 14 | P1: Month 15 | Q1: Month 16 | R1: Month 17 | S1: Month 18 | T1: Month 19 | U1: Month 20 | V1: Month 21 | W1: Month 22 | X1: Month 23 | Y1: Month 24
A2: REVENUE | B2: ='Revenue Model'!B14 -> 5473399.2 | C2: ='Revenue Model'!C14 -> 5559661.8 | D2: ='Revenue Model'!D14 -> 5603958.8 | E2: ='Revenue Model'!E14 -> 5648255.8 | F2: ='Revenue Model'!F14 -> 5692552.8 | G2: ='Revenue Model'!G14 -> 5737626.9 | H2: ='Revenue Model'!H14 -> 5782701 | I2: ='Revenue Model'!I14 -> 5827775.2 | ... Y2: ='Revenue Model'!Y14 -> 6608801.2
A3: COST OF GOODS SOLD | B3: =B2-(B2*0.72) -> 1532551.8 | C3: =C2-(C2*0.72) -> 1556705.3 | D3: =D2-(D2*0.72) -> 1569108.5 | E3: =E2-(E2*0.72) -> 1581511.6 | F3: =F2-(F2*0.72) -> 1593914.8 | G3: =G2-(G2*0.72) -> 1606535.5 | H3: =H2-(H2*0.72) -> 1619156.3 | I3: =I2-(I2*0.72) -> 1631777.1 | ... Y3: =Y2-(Y2*0.72) -> 1850464.3
A4: GROSS PROFIT | B4: =B2-B3 -> 3940847.4 | C4: =C2-C3 -> 4002956.5 | D4: =D2-D3 -> 4034850.3 | E4: =E2-E3 -> 4066744.2 | F4: =F2-F3 -> 4098638 | G4: =G2-G3 -> 4131091.4 | H4: =H2-H3 -> 4163544.8 | I4: =I2-I3 -> 4195998.1 | ... Y4: =Y2-Y3 -> 4758336.9
A5: OPERATING EXPENSE | B5: =B2*SUM(Assumptions!$B$11:$B$13) -> 2736699.6 | C5: =C2*SUM(Assumptions!$B$11:$B$13) -> 2779830.9 | D5: =D2*SUM(Assumptions!$B$11:$B$13) -> 2801979.4 | E5: =E2*SUM(Assumptions!$B$11:$B$13) -> 2824127.9 | F5: =F2*SUM(Assumptions!$B$11:$B$13) -> 2846276.4 | G5: =G2*SUM(Assumptions!$B$11:$B$13) -> 2868813.5 | H5: =H2*SUM(Assumptions!$B$11:$B$13) -> 2891350.5 | I5: =I2*SUM(Assumptions!$B$11:$B$13) -> 2913887.6 | ... Y5: =Y2*SUM(Assumptions!$B$11:$B$13) -> 3304400.6
A6: EBITDA | B6: =B4-B5 -> 1204147.8 | C6: =C4-C5 -> 1223125.6 | D6: =D4-D5 -> 1232870.9 | E6: =E4-E5 -> 1242616.3 | F6: =F4-F5 -> 1252361.6 | G6: =G4-G5 -> 1262277.9 | H6: =H4-H5 -> 1272194.2 | I6: =I4-I5 -> 1282110.5 | ... Y6: =Y4-Y5 -> 1453936.3
A7: NET INCOME | B7: =B6*(1-0.25) -> 903110.87 | C7: =C6*(1-0.25) -> 917344.19 | D7: =D6*(1-0.25) -> 924653.2 | E7: =E6*(1-0.25) -> 931962.2 | F7: =F6*(1-0.25) -> 939271.21 | G7: =G6*(1-0.25) -> 946708.44 | H7: =H6*(1-0.25) -> 954145.67 | I7: =I6*(1-0.25) -> 961582.9 | ... Y7: =Y6*(1-0.25) -> 1090452.2

Sheet Balance Sheet
A1: Balance Sheet | B1: Month 1 | C1: Month 2 | D1: Month 3 | E1: Month 4 | F1: Month 5 | G1: Month 6 | H1: Month 7 | I1: Month 8 | J1: Month 9 | K1: Month 10 | L1: Month 11 | M1: Month 12 | N1: Month 13 | O1: Month 14 | P1: Month 15 | Q1: Month 16 | R1: Month 17 | S1: Month 18 | T1: Month 19 | U1: Month 20 | V1: Month 21 | W1: Month 22 | X1: Month 23 | Y1: Month 24
A3: ASSETS
A4: Cash & Equivalents | B4: ='P&L'!B7 -> 903110.87 | C4: ='P&L'!C7 -> 917344.19 | D4: ='P&L'!D7 -> 924653.2 | E4: ='P&L'!E7 -> 931962.2 | F4: ='P&L'!F7 -> 939271.21 | G4: ='P&L'!G7 -> 946708.44 | H4: ='P&L'!H7 -> 954145.67 | I4: ='P&L'!I7 -> 961582.9 | ... Y4: ='P&L'!Y7 -> 1090452.2
A5: Accounts Receivable | B5: =('Revenue Model'!B13)*1/12 -> 38009.717 | C5: =('Revenue Model'!C13)*1/12 -> 38608.762 | D5: =('Revenue Model'!D13)*1/12 -> 38916.38 | E5: =('Revenue Model'!E13)*1/12 -> 39223.998 | F5: =('Revenue Model'!F13)*1/12 -> 39531.616 | G5: =('Revenue Model'!G13)*1/12 -> 39844.631 | H5: =('Revenue Model'!H13)*1/12 -> 40157.646 | I5: =('Revenue Model'!I13)*1/12 -> 40470.661 | ... Y5: =('Revenue Model'!Y13)*1/12 -> 45894.453
A6: Total Current Assets | B6: =SUM(B4:B5) -> 941120.58 | C6: =SUM(C4:C5) -> 955952.96 | D6: =SUM(D4:D5) -> 963569.58 | E6: =SUM(E4:E5) -> 971186.2 | F6: =SUM(F4:F5) -> 978802.82 | G6: =SUM(G4:G5) -> 986553.07 | H6: =SUM(H4:H5) -> 994303.32 | I6: =SUM(I4:I5) -> 1002053.6 | ... Y6: =SUM(Y4:Y5) -> 1136346.6
A8: Total Assets | B8: =B6 -> 941120.58 | C8: =C6 -> 955952.96 | D8: =D6 -> 963569.58 | E8: =E6 -> 971186.2 | F8: =F6 -> 978802.82 | G8: =G6 -> 986553.07 | H8: =H6 -> 994303.32 | I8: =I6 -> 1002053.6 | ... Y8: =Y6 -> 1136346.6
A10: LIABILITIES
A11: Deferred Revenue | B11: =('Revenue Model'!B13)*1/12 -> 38009.717 | C11: =('Revenue Model'!C13)*1/12 -> 38608.762 | D11: =('Revenue Model'!D13)*1/12 -> 38916.38 | E11: =('Revenue Model'!E13)*1/12 -> 39223.998 | F11: =('Revenue Model'!F13)*1/12 -> 39531.616 | G11: =('Revenue Model'!G13)*1/12 -> 39844.631 | H11: =('Revenue Model'!H13)*1/12 -> 40157.646 | I11: =('Revenue Model'!I13)*1/12 -> 40470.661 | ... Y11: =('Revenue Model'!Y13)*1/12 -> 45894.453
A12: Total Current Liabilities | B12: =SUM(B11:B11) -> 38009.717 | C12: =SUM(C11:C11) -> 38608.762 | D12: =SUM(D11:D11) -> 38916.38 | E12: =SUM(E11:E11) -> 39223.998 | F12: =SUM(F11:F11) -> 39531.616 | G12: =SUM(G11:G11) -> 39844.631 | H12: =SUM(H11:H11) -> 40157.646 | I12: =SUM(I11:I11) -> 40470.661 | ... Y12: =SUM(Y11:Y11) -> 45894.453
A14: EQUITY
A15: Retained Earnings | B15: ='P&L'!B7 -> 903110.87 | C15: ='P&L'!C7 -> 917344.19 | D15: ='P&L'!D7 -> 924653.2 | E15: ='P&L'!E7 -> 931962.2 | F15: ='P&L'!F7 -> 939271.21 | G15: ='P&L'!G7 -> 946708.44 | H15: ='P&L'!H7 -> 954145.67 | I15: ='P&L'!I7 -> 961582.9 | ... Y15: ='P&L'!Y7 -> 1090452.2
A16: Total Equity | B16: =B15 -> 903110.87 | C16: =C15 -> 917344.19 | D16: =D15 -> 924653.2 | E16: =E15 -> 931962.2 | F16: =F15 -> 939271.21 | G16: =G15 -> 946708.44 | H16: =H15 -> 954145.67 | I16: =I15 -> 961582.9 | ... Y16: =Y15 -> 1090452.2
A18: TOTAL LIABILITIES + EQUITY | B18: =B16+B12 -> 941120.58 | C18: =C16+C12 -> 955952.96 | D18: =D16+D12 -> 963569.58 | E18: =E16+E12 -> 971186.2 | F18: =F16+F12 -> 978802.82 | G18: =G16+G12 -> 986553.07 | H18: =H16+H12 -> 994303.32 | I18: =I16+I12 -> 1002053.6 | ... Y18: =Y16+Y12 -> 1136346.6

Sheet Cash Flow
A1: CASH FLOW STATEMENT | B1: Month 1 | C1: Month 2 | D1: Month 3 | E1: Month 4 | F1: Month 5 | G1: Month 6 | H1: Month 7 | I1: Month 8 | J1: Month 9 | K1: Month 10 | L1: Month 11 | M1: Month 12 | N1: Month 13 | O1: Month 14 | P1: Month 15 | Q1: Month 16 | R1: Month 17 | S1: Month 18 | T1: Month 19 | U1: Month 20 | V1: Month 21 | W1: Month 22 | X1: Month 23 | Y1: Month 24
A3: OPERATING ACTIVITIES
A4: Net Income | B4: ='P&L'!B7 -> 903110.87 | C4: ='P&L'!C7 -> 917344.19 | D4: ='P&L'!D7 -> 924653.2 | E4: ='P&L'!E7 -> 931962.2 | F4: ='P&L'!F7 -> 939271.21 | G4: ='P&L'!G7 -> 946708.44 | H4: ='P&L'!H7 -> 954145.67 | I4: ='P&L'!I7 -> 961582.9 | ... Y4: ='P&L'!Y7 -> 1090452.2
A5: Add: Depreciation & Amortization | B5: ='Revenue Model'!B14*0.02 -> 109467.98 | C5: ='Revenue Model'!C14*0.02 -> 111193.24 | D5: ='Revenue Model'!D14*0.02 -> 112079.18 | E5: ='Revenue Model'!E14*0.02 -> 112965.12 | F5: ='Revenue Model'!F14*0.02 -> 113851.06 | G5: ='Revenue Model'!G14*0.02 -> 114752.54 | H5: ='Revenue Model'!H14*0.02 -> 115654.02 | I5: ='Revenue Model'!I14*0.02 -> 116555.5 | ... Y5: ='Revenue Model'!Y14*0.02 -> 132176.02
A6: Change in Accounts Receivable | B6: =-('Balance Sheet'!B5-0) -> -38009.717 | C6: =-('Balance Sheet'!C5-0) -> -38608.762 | D6: =-('Balance Sheet'!D5-0) -> -38916.38 | E6: =-('Balance Sheet'!E5-0) -> -39223.998 | F6: =-('Balance Sheet'!F5-0) -> -39531.616 | G6: =-('Balance Sheet'!G5-0) -> -39844.631 | H6: =-('Balance Sheet'!H5-0) -> -40157.646 | I6: =-('Balance Sheet'!I5-0) -> -40470.661 | ... Y6: =-('Balance Sheet'!Y5-0) -> -45894.453
A7: Change in Deferred Revenue | B7: ='Balance Sheet'!B11 -> 38009.717 | C7: ='Balance Sheet'!C11 -> 38608.762 | D7: ='Balance Sheet'!D11 -> 38916.38 | E7: ='Balance Sheet'!E11 -> 39223.998 | F7: ='Balance Sheet'!F11 -> 39531.616 | G7: ='Balance Sheet'!G11 -> 39844.631 | H7: ='Balance Sheet'!H11 -> 40157.646 | I7: ='Balance Sheet'!I11 -> 40470.661 | ... Y7: ='Balance Sheet'!Y11 -> 45894.453
A8: Total Operating Cash Flow | B8: =SUM(B4:B7) -> 1012578.9 | C8: =SUM(C4:C7) -> 1028537.4 | D8: =SUM(D4:D7) -> 1036732.4 | E8: =SUM(E4:E7) -> 1044927.3 | F8: =SUM(F4:F7) -> 1053122.3 | G8: =SUM(G4:G7) -> 1061461 | H8: =SUM(H4:H7) -> 1069799.7 | I8: =SUM(I4:I7) -> 1078138.4 | ... Y8: =SUM(Y4:Y7) -> 1222628.2
A10: INVESTING ACTIVITIES
A11: Capital Expenditure | B11: ='Revenue Model'!B14*0.05 -> 273669.96 | C11: ='Revenue Model'!C14*0.05 -> 277983.09 | D11: ='Revenue Model'!D14*0.05 -> 280197.94 | E11: ='Revenue Model'!E14*0.05 -> 282412.79 | F11: ='Revenue Model'!F14*0.05 -> 284627.64 | G11: ='Revenue Model'!G14*0.05 -> 286881.35 | H11: ='Revenue Model'!H14*0.05 -> 289135.05 | I11: ='Revenue Model'!I14*0.05 -> 291388.76 | ... Y11: ='Revenue Model'!Y14*0.05 -> 330440.06
A12: Total Investing Cash Flow | B12: =B11 -> 273669.96 | C12: =C11 -> 277983.09 | D12: =D11 -> 280197.94 | E12: =E11 -> 282412.79 | F12: =F11 -> 284627.64 | G12: =G11 -> 286881.35 | H12: =H11 -> 289135.05 | I12: =I11 -> 291388.76 | ... Y12: =Y11 -> 330440.06
A14: FINANCING ACTIVITIES
A15: Equity Financing | B15: =0 -> 0 | C15: =0 -> 0 | D15: =0 -> 0 | E15: =0 -> 0 | F15: =0 -> 0 | G15: =0 -> 0 | H15: =0 -> 0 | I15: =0 -> 0 | ... Y15: =0 -> 0
A16: Total Financing Cash Flow | B16: =0 -> 0 | C16: =0 -> 0 | D16: =0 -> 0 | E16: =0 -> 0 | F16: =0 -> 0 | G16: =0 -> 0 | H16: =0 -> 0 | I16: =0 -> 0 | ... Y16: =0 -> 0
A18: NET CASH FLOW | B18: =B16+B12+B8 -> 1286248.8 | C18: =C16+C12+C8 -> 1306520.5 | D18: =D16+D12+D8 -> 1316930.3 | E18: =E16+E12+E8 -> 1327340.1 | F18: =F16+F12+F8 -> 1337749.9 | G18: =G16+G12+G8 -> 1348342.3 | H18: =H16+H12+H8 -> 1358934.7 | I18: =I16+I12+I8 -> 1369527.2 | ... Y18: =Y16+Y12+Y8 -> 1553068.3
A19: Opening Cash Balance | B19: =0 -> 0 | C19: =B20 -> 1286248.8 | D19: =C20 -> 2592769.3 | E19: =D20 -> 3909699.6 | F19: =E20 -> 5237039.7 | G19: =F20 -> 6574789.6 | H19: =G20 -> 7923132 | I19: =H20 -> 9282066.7 | J19: =I20 -> 10651594 | ... Y19: =X20 -> 32542844
A20: CLOSING CASH BALANCE | B20: =B19+B18 -> 1286248.8 | C20: =C19+C18 -> 2592769.3 | D20: =D19+D18 -> 3909699.6 | E20: =E19+E18 -> 5237039.7 | F20: =F19+F18 -> 6574789.6 | G20: =G19+G18 -> 7923132 | H20: =H19+H18 -> 9282066.7 | I20: =I19+I18 -> 10651594 | ... Y20: =Y19+Y18 -> 34095912

Sheet Scenerios
A1: SCENARIO ANALYSIS
A3: ASSUMPTIONS | B3: BASE CASE | C3: BULL CASE | D3: BEAR CASE
A4: Monthly Growth Rate | B4: 0.03 | C4: 0.05 | D4: 0.01
A5: Annual Churn Rate | B5: 0.2654 | C5: 0.2 | D5: 0.35
A6: Gross Margin % | B6: 0.72 | C6: 0.75 | D6: 0.65
A12: OUTPUTS
A13: Year 1 ARR | B13: 6014288.9 | C13: 8113344.8 | D13: 4339551.5
A14: Year 2 ARR | B14: 6608801.2 | C14: 12023915 | D14: 3440400.2
A15: Year 1 Net Income | B15: 992357.66 | C15: 1338701.9 | D15: 716026
A16: Year 2 Net Income | B16: 1090452.2 | C16: 1983946 | D16: 567666.02
A17: Year 1 Cash Flow | B17: 16238914 | C17: 19183790 | D17: 13666234
A18: Year 2 Cash Flow | B18: 34095912 | C18: 47677954 | D18: 24482010

Sheet Monte Carlo
A1: MONTE CARLO SIMULATION
A3: PARAMETERS
A4: Mean Growth Rate | B4: 0.03
A5: Growth Rate Std Dev | B5: 0.01
A6: Mean Churn Rate | B6: 0.2654
A7: Churn Rate Std Dev | B7: 0.05
A9: RESULTS
A10: Number of Simulations | B10: 1000
A13: Simulation # | B13: Random Growth Rate | C13: Random Churn Rate | D13: Year 2 MRR | E13: Year 2 ARR
A14: 1 | B14: =_xlfn.NORM.INV(RAND(), $B$4, $B$5) -> 0.046541649 | C14: =+_xlfn.NORM.INV(RAND(), $B$6, $B$7) -> 0.22541932 | D14: =Assumptions!B$3*(1+B14)^24*(1-C14/12)^24 -> 862130.83 | E14: =D14*12 -> 10345570
A15: 2 | B15: =_xlfn.NORM.INV(RAND(), $B$4, $B$5) -> 0.038621052 | C15: =+_xlfn.NORM.INV(RAND(), $B$6, $B$7) -> 0.32640195 | D15: =Assumptions!B$3*(1+B15)^24*(1-C15/12)^24 -> 584265.88 | E15: =D15*12 -> 7011190.6
A16: 3 | B16: =_xlfn.NORM.INV(RAND(), $B$4, $B$5) -> 0.021635069 | C16: =+_xlfn.NORM.INV(RAND(), $B$6, $B$7) -> 0.24727141 | D16: =Assumptions!B$3*(1+B16)^24*(1-C16/12)^24 -> 462544.96 | E16: =D16*12 -> 5550539.5
A17: 4 | B17: =_xlfn.NORM.INV(RAND(), $B$4, $B$5) -> 0.033347174 | C17: =+_xlfn.NORM.INV(RAND(), $B$6, $B$7) -> 0.22034549 | D17: =Assumptions!B$3*(1+B17)^24*(1-C17/12)^24 -> 642417.55 | E17: =D17*12 -> 7709010.5
A18: 5 | B18: =_xlfn.NORM.INV(RAND(), $B$4, $B$5) -> 0.026268525 | C18: =+_xlfn.NORM.INV(RAND(), $B$6, $B$7) -> 0.22163559 | D18: =Assumptions!B$3*(1+B18)^24*(1-C18/12)^24 -> 543287.72 | E18: =D18*12 -> 6519452.7
A19: 6 | B19: =_xlfn.NORM.INV(RAND(), $B$4, $B$5) -> 0.016545754 | C19: =+_xlfn.NORM.INV(RAND(), $B$6, $B$7) -> 0.24958473 | D19: =Assumptions!B$3*(1+B19)^24*(1-C19/12)^24 -> 408365.91 | E19: =D19*12 -> 4900390.9
A20: 7 | B20: =_xlfn.NORM.INV(RAND(), $B$4, $B$5) -> 0.030043042 | C20: =+_xlfn.NORM.INV(RAND(), $B$6, $B$7) -> 0.17554149 | D20: =Assumptions!B$3*(1+B20)^24*(1-C20/12)^24 -> 651636.21 | E20: =D20*12 -> 7819634.6
A21: 8 | B21: =_xlfn.NORM.INV(RAND(), $B$4, $B$5) -> 0.012478112 | C21: =+_xlfn.NORM.INV(RAND(), $B$6, $B$7) -> 0.23283676 | D21: =Assumptions!B$3*(1+B21)^24*(1-C21/12)^24 -> 383799.22 | E21: =D21*12 -> 4605590.6
A22: 9 | B22: =_xlfn.NORM.INV(RAND(), $B$4, $B$5) -> 0.033818328 | C22: =+_xlfn.NORM.INV(RAND(), $B$6, $B$7) -> 0.20999838 | D22: =Assumptions!B$3*(1+B22)^24*(1-C22/12)^24 -> 663315.56 | E22: =D22*12 -> 7959786.7
A23: 10 | B23: =_xlfn.NORM.INV(RAND(), $B$4, $B$5) -> 0.032019105 | C23: =+_xlfn.NORM.INV(RAND(), $B$6, $B$7) -> 0.21177241 | D23: =Assumptions!B$3*(1+B23)^24*(1-C23/12)^24 -> 633863.81 | E23: =D23*12 -> 7606365.7
A24: 11 | B24: =_xlfn.NORM.INV(RAND(), $B$4, $B$5) -> 0.035407585 | C24: =+_xlfn.NORM.INV(RAND(), $B$6, $B$7) -> 0.27161059 | D24: =Assumptions!B$3*(1+B24)^24*(1-C24/12)^24 -> 606902.93 | E24: =D24*12 -> 7282835.2
A25: 12 | B25: =_xlfn.NORM.INV(RAND(), $B$4, $B$5) -> 0.040697449 | C25: =+_xlfn.NORM.INV(RAND(), $B$6, $B$7) -> 0.31434013 | D25: =Assumptions!B$3*(1+B25)^24*(1-C25/12)^24 -> 628335.4 | E25: =D25*12 -> 7540024.8
... A1013: 1000 | B1013: =_xlfn.NORM.INV(RAND(), $B$4, $B$5) -> 0.021998647 | C1013: =+_xlfn.NORM.INV(RAND(), $B$6, $B$7) -> 0.17009805 | D1013: =Assumptions!B$3*(1+B1013)^24*(1-C1013/12)^24 -> 545859.86 | E1013: =D1013*12 -> 6550318.3
A1015: SIMULATION RESULTS
A1016: Mean Year 2 ARR | B1016: =AVERAGE(E14:E1013) -> 6710773.2
A1017: P10 (worst 10%) | B1017: =PERCENTILE(E14:E1013,0.1) -> 4520187.3
A1018: P50 (median) | B1018: =PERCENTILE(E14:E1013,0.5) -> 6511809.6
A1019: P90 (best 10%) | B1019: =PERCENTILE(E14:E1013,0.9) -> 9073744.2
A1020: Min ARR | B1020: =MIN(E14:E1013) -> 3055864.8
A1021: Max ARR | B1021: =MAX(E14:E1013) -> 13325505

Sheet Dashboard
A1: Starting ARR | B1: Year 2 ARR | C1: Net Income (Year 2) | D1: Cash Balance (Year 2)
A2: ='Revenue Model'!B14 -> 5473399.2 | B2: ='Revenue Model'!Y14 -> 6608801.2 | C2: ='P&L'!Y7 -> 1090452.2 | D2: ='Cash Flow'!Y20 -> 34095912
